streamstockspy/__init__.py.py
streamstockspy/stocks.py
streamstockspy-0.0.4.dist-info/LICENSE.txt
streamstockspy-0.0.4.dist-info/METADATA
streamstockspy-0.0.4.dist-info/WHEEL
streamstockspy-0.0.4.dist-info/top_level.txt
streamstockspy-0.0.4.dist-info/RECORD
