Metadata-Version: 2.1
Name: streamstockspy
Version: 0.0.4
Summary: Library for Live stocks and historical data.
Home-page: https://github.com/antoinech13/Stocks
Author: Antoine and Lockas
Author-email: antoine-spartan@hotmail.fr
License: UNKNOWN
Platform: UNKNOWN
Classifier: Programming Language :: Python :: 3
Classifier: License :: OSI Approved :: MIT License
Classifier: Operating System :: OS Independent
Requires-Python: >=3.6
Requires-Dist: numpy
Requires-Dist: bs4
Requires-Dist: requests
Requires-Dist: plotly
Requires-Dist: matplotlib
Requires-Dist: win10toast
Requires-Dist: yfinance
